AUTHORS.rst
CONTRIBUTING.rst
LICENSE
MANIFEST.in
README.rst
requirements.txt
setup.cfg
setup.py
versioneer.py
asterogap/GP.py
asterogap/__init__.py
asterogap/_version.py
asterogap/lombscargle.py
asterogap/run_gp.py
asterogap/run_plotting.py
asterogap.egg-info/PKG-INFO
asterogap.egg-info/SOURCES.txt
asterogap.egg-info/dependency_links.txt
asterogap.egg-info/entry_points.txt
asterogap.egg-info/requires.txt
asterogap.egg-info/top_level.txt
asterogap/tests/__init__.py
asterogap/tests/conftest.py
asterogap/tests/test_GP.py
asterogap/tests/test_run_gp.py
docs/Makefile
docs/make.bat
docs/source/conf.py
docs/source/index.rst
docs/source/installation.rst
docs/source/min_versions.rst
docs/source/release-history.rst
docs/source/usage.rst