Metadata-Version: 1.2
Name: asterogap
Version: 0.1
Summary: AsteroGaP (Asteroid Gaussian Processes) is a Bayesian-based Gaussian Process model that seeks to fit sparsely-sampled asteroid light curves.
Home-page: https://github.com/dirac-institute/asterogap
Author: Christina Willecke Lindberg
Author-email: clindbe2@jhu.edu
License: BSD (3-clause)
Platform: UNKNOWN
Classifier: Development Status :: 2 - Pre-Alpha
Classifier: Natural Language :: English
Classifier: Programming Language :: Python :: 3
Requires-Python: >=3.6
